checkforai/__init__.py
checkforai/text_classifier.py
checkforai-0.2.0.dist-info/LICENSE
checkforai-0.2.0.dist-info/METADATA
checkforai-0.2.0.dist-info/WHEEL
checkforai-0.2.0.dist-info/RECORD
